{
  "_class": "text",
  "attributedString": {
    "_class": "attributedString",
    "attributes": [
      {
        "_class": "stringAttribute",
        "attributes": {
          "MSAttributedStringColorAttribute": {
            "_class": "color",
            "alpha": 1,
            "blue": 0.7998962998390198,
            "green": 0.8000451326370239,
            "red": 0.7999318838119507
          },
          "MSAttributedStringFontAttribute": {
            "_class": "fontDescriptor",
            "attributes": {
              "name": "AppleSDGothicNeo-Regular",
              "size": 14
            }
          },
          "paragraphStyle": {
            "_class": "paragraphStyle",
            "alignment": 1
          },
          "textStyleVerticalAlignmentKey": 1
        },
        "length": 6,
        "location": 0
      }
    ],
    "string": "분위기 설정"
  },
  "automaticallyDrawOnUnderlyingPath": false,
  "booleanOperation": -1,
  "clippingMaskMode": 0,
  "do_objectID": "1CEC1437-0922-4B13-8C9A-D5CDD9E51A78",
  "dontSynchroniseWithSymbol": false,
  "exportOptions": {
    "_class": "exportOptions",
    "do_objectID": "5395FB3C-60F8-4290-88AF-1894C0BE7551",
    "exportFormats": [
    ],
    "includedLayerIds": [
    ],
    "layerOptions": 0,
    "shouldTrim": false
  },
  "frame": {
    "_class": "rect",
    "constrainProportions": false,
    "do_objectID": "63D6C40A-5978-4CD9-907A-EC796B09EEFE",
    "height": 17,
    "width": 65,
    "x": 0,
    "y": 8
  },
  "glyphBounds": "{{0, 1}, {63, 13}}",
  "hasClippingMask": false,
  "isFixedToViewport": false,
  "isFlippedHorizontal": false,
  "isFlippedVertical": false,
  "isLocked": false,
  "isVisible": true,
  "layerListExpandedType": 0,
  "lineSpacingBehaviour": 2,
  "name": "분위기 설정",
  "nameIsFixed": false,
  "resizingConstraint": 47,
  "resizingType": 0,
  "rotation": 0,
  "shouldBreakMaskChain": false,
  "style": {
    "_class": "style",
    "do_objectID": "8CA5EB53-2FD0-47D3-BB7D-8FCBC3B313D2",
    "endMarkerType": 0,
    "miterLimit": 10,
    "startMarkerType": 0,
    "textStyle": {
      "_class": "textStyle",
      "do_objectID": "6BB63CFE-95F3-4EDE-8E00-AA6C5EA137E2",
      "encodedAttributes": {
        "MSAttributedStringColorAttribute": {
          "_class": "color",
          "alpha": 1,
          "blue": 0.7998962998390198,
          "green": 0.8000451326370239,
          "red": 0.7999318838119507
        },
        "MSAttributedStringFontAttribute": {
          "_class": "fontDescriptor",
          "attributes": {
            "name": "AppleSDGothicNeo-Regular",
            "size": 14
          }
        },
        "paragraphStyle": {
          "_class": "paragraphStyle",
          "alignment": 1
        },
        "textStyleVerticalAlignmentKey": 1
      },
      "verticalAlignment": 1
    },
    "windingRule": 1
  },
  "textBehaviour": 0,
  "userInfo": {
    "com.animaapp.stc-sketch-plugin": {
      "kModelPropertiesKey": {
        "isAutoWidth": 1
      }
    }
  }
}