{
  "_class": "symbolInstance",
  "booleanOperation": -1,
  "clippingMaskMode": 0,
  "do_objectID": "922ED963-44F1-4827-9A18-ADD64F1F8676",
  "exportOptions": {
    "_class": "exportOptions",
    "do_objectID": "45C9D337-CCB5-4556-9170-49B4AD2AA6DB",
    "exportFormats": [
    ],
    "includedLayerIds": [
    ],
    "layerOptions": 0,
    "shouldTrim": false
  },
  "frame": {
    "_class": "rect",
    "constrainProportions": false,
    "do_objectID": "C8C6D7EB-9F29-405D-90B6-3BCAD05B7292",
    "height": 25,
    "width": 185,
    "x": 109,
    "y": 0
  },
  "hasClippingMask": false,
  "horizontalSpacing": 0,
  "isFixedToViewport": false,
  "isFlippedHorizontal": false,
  "isFlippedVertical": false,
  "isLocked": false,
  "isVisible": true,
  "layerListExpandedType": 0,
  "name": "Editor/__Rec/__card Copy",
  "nameIsFixed": false,
  "overrideValues": [
    {
      "_class": "overrideValue",
      "do_objectID": "C02BE7CA-15A9-4376-97C0-50850C64CCBE",
      "overrideName": "CB0C4998-9C53-49D0-B023-CAE971CFDCF7_stringValue",
      "value": "북엇국에는 미역 줄기랑 어울려"
    }
  ],
  "resizingConstraint": 63,
  "resizingType": 0,
  "rotation": 0,
  "scale": 1,
  "shouldBreakMaskChain": false,
  "style": {
    "_class": "style",
    "do_objectID": "BFD59C52-43B4-453E-9B14-E29EA93C7637",
    "endMarkerType": 0,
    "miterLimit": 10,
    "startMarkerType": 0,
    "windingRule": 1
  },
  "symbolID": "B52A62E7-9D4C-4D56-8EFE-CD6E7466B3DC",
  "userInfo": {
    "com.animaapp.stc-sketch-plugin": {
      "kModelPropertiesKey": {
        "size.update": 1543478540.305478
      }
    }
  },
  "verticalSpacing": 0
}