{
  "_class": "group",
  "booleanOperation": -1,
  "clippingMaskMode": 0,
  "do_objectID": "5614868A-BF7D-40A9-86D7-F3E19A2AF4A7",
  "exportOptions": {
    "_class": "exportOptions",
    "do_objectID": "3AB6C1BB-409B-4B27-B380-6369A44939AE",
    "exportFormats": [
    ],
    "includedLayerIds": [
    ],
    "layerOptions": 0,
    "shouldTrim": false
  },
  "frame": {
    "_class": "rect",
    "constrainProportions": false,
    "do_objectID": "88EBDDA0-47E6-4560-AB96-30F5B2F85AEC",
    "height": 25,
    "width": 203,
    "x": 0,
    "y": 87
  },
  "hasClickThrough": false,
  "hasClippingMask": false,
  "isFixedToViewport": false,
  "isFlippedHorizontal": false,
  "isFlippedVertical": false,
  "isLocked": false,
  "isVisible": true,
  "layerListExpandedType": 0,
  "layers": [
    {
      "class": "symbolInstance",
      "id": "EC91A1CF-42AA-4826-9A75-AD79C81226BE"
    },
    {
      "class": "symbolInstance",
      "id": "97616960-3609-4908-92F6-B4DD204D3B54"
    },
    {
      "class": "symbolInstance",
      "id": "FAB1F7CC-01E7-4C62-985E-6CDB670E407F"
    }
  ],
  "name": "Stacked Group Copy",
  "nameIsFixed": false,
  "resizingConstraint": 63,
  "resizingType": 0,
  "rotation": 0,
  "shouldBreakMaskChain": false,
  "style": {
    "_class": "style",
    "do_objectID": "06E5FF91-35D9-409E-B7D5-4F94A6FEA533",
    "endMarkerType": 0,
    "miterLimit": 10,
    "startMarkerType": 0,
    "windingRule": 1
  },
  "userInfo": {
    "com.animaapp.stc-sketch-plugin": {
      "kModelPropertiesKey": {
        "isCollapsing": 1,
        "resizesContainer": 1,
        "spacing": 4,
        "stackType": 1
      },
      "kViewTypeKey": "ADModelStackView"
    }
  }
}