{
  "_class": "group",
  "booleanOperation": -1,
  "clippingMaskMode": 0,
  "do_objectID": "03AC9A76-CC75-48F5-BF45-26923ED36BD7",
  "exportOptions": {
    "_class": "exportOptions",
    "do_objectID": "1DA8A6C1-100A-4E56-8C7A-A9C2B53E930C",
    "exportFormats": [
    ],
    "includedLayerIds": [
    ],
    "layerOptions": 0,
    "shouldTrim": false
  },
  "frame": {
    "_class": "rect",
    "constrainProportions": false,
    "do_objectID": "71BAE73C-2E7C-4987-BA66-B04D1FCC5691",
    "height": 54,
    "width": 632,
    "x": 80,
    "y": 233
  },
  "hasClickThrough": false,
  "hasClippingMask": false,
  "isFixedToViewport": false,
  "isFlippedHorizontal": false,
  "isFlippedVertical": false,
  "isLocked": false,
  "isVisible": true,
  "layerListExpandedType": 0,
  "layers": [
    {
      "class": "rectangle",
      "id": "FE9D94DC-852F-43D5-9FEC-9ADB7CE459AE"
    },
    {
      "class": "rectangle",
      "id": "C07DA475-2458-47B4-A323-46DA3D213386"
    },
    {
      "class": "group",
      "id": "FBEFBCD5-C55D-4B8D-8BC7-E0A69B0D568C"
    },
    {
      "class": "group",
      "id": "FD661201-8E8A-438E-95FE-35AE67FE3B41"
    }
  ],
  "name": "Group",
  "nameIsFixed": false,
  "resizingConstraint": 63,
  "resizingType": 0,
  "rotation": 0,
  "shouldBreakMaskChain": false,
  "style": {
    "_class": "style",
    "do_objectID": "744F4319-D582-4AB7-900C-82DB862CFE8B",
    "endMarkerType": 0,
    "miterLimit": 10,
    "startMarkerType": 0,
    "windingRule": 1
  },
  "userInfo": {
    "com.animaapp.stc-sketch-plugin": {
      "kModelPropertiesKey": {
      }
    }
  }
}