{
  "_class": "group",
  "booleanOperation": -1,
  "clippingMaskMode": 0,
  "do_objectID": "DCA9448E-13F5-4647-ADD1-297FDFE5D2E0",
  "exportOptions": {
    "_class": "exportOptions",
    "do_objectID": "461503C6-7681-48F5-8A0C-DF49B80425B6",
    "exportFormats": [
    ],
    "includedLayerIds": [
    ],
    "layerOptions": 0,
    "shouldTrim": false
  },
  "frame": {
    "_class": "rect",
    "constrainProportions": false,
    "do_objectID": "1462E695-9568-4327-9E1D-7FBB4C1EFEEE",
    "height": 17,
    "width": 61,
    "x": 0,
    "y": 31
  },
  "hasClickThrough": false,
  "hasClippingMask": false,
  "isFixedToViewport": false,
  "isFlippedHorizontal": false,
  "isFlippedVertical": false,
  "isLocked": false,
  "isVisible": true,
  "layerListExpandedType": 0,
  "layers": [
    {
      "class": "text",
      "id": "FBAF704A-2689-4CE0-B0CD-1A53F9E11B6B"
    },
    {
      "class": "rectangle",
      "id": "475C7CEF-0E4F-4719-A619-608E6729455E"
    }
  ],
  "name": "Group 4 Copy 4",
  "nameIsFixed": false,
  "resizingConstraint": 63,
  "resizingType": 0,
  "rotation": 0,
  "shouldBreakMaskChain": false,
  "style": {
    "_class": "style",
    "do_objectID": "0A281D5D-EC22-4F82-A453-8863CE135937",
    "endMarkerType": 0,
    "miterLimit": 10,
    "startMarkerType": 0,
    "windingRule": 1
  },
  "userInfo": {
    "com.animaapp.stc-sketch-plugin": {
      "kModelPropertiesKey": {
      }
    }
  }
}