{
  "_class": "group",
  "booleanOperation": -1,
  "clippingMaskMode": 0,
  "do_objectID": "F0EAE80B-455F-4A8B-ABE2-A4EF75404231",
  "exportOptions": {
    "_class": "exportOptions",
    "do_objectID": "F23BF8BC-04CB-42B9-84D2-A46C5C4D0E5F",
    "exportFormats": [
    ],
    "includedLayerIds": [
    ],
    "layerOptions": 0,
    "shouldTrim": false
  },
  "frame": {
    "_class": "rect",
    "constrainProportions": false,
    "do_objectID": "5C672BEA-5D3B-4BBB-81BA-257736EDDA7A",
    "height": 25,
    "width": 203,
    "x": 0,
    "y": 87
  },
  "hasClickThrough": false,
  "hasClippingMask": false,
  "isFixedToViewport": false,
  "isFlippedHorizontal": false,
  "isFlippedVertical": false,
  "isLocked": false,
  "isVisible": true,
  "layerListExpandedType": 2,
  "layers": [
    {
      "class": "symbolInstance",
      "id": "20C876BE-4A2A-4E0B-AB21-71C9B6F246B9"
    },
    {
      "class": "symbolInstance",
      "id": "07D6A220-124F-4586-A324-DF6A0398976E"
    },
    {
      "class": "symbolInstance",
      "id": "E41FC846-82C1-4578-B12B-2ACE1E605FA7"
    }
  ],
  "name": "Stacked Group Copy",
  "nameIsFixed": false,
  "resizingConstraint": 63,
  "resizingType": 0,
  "rotation": 0,
  "shouldBreakMaskChain": false,
  "style": {
    "_class": "style",
    "do_objectID": "1CA8A4B9-3F5D-4E45-B04B-FD3C34CDFA80",
    "endMarkerType": 0,
    "miterLimit": 10,
    "startMarkerType": 0,
    "windingRule": 1
  },
  "userInfo": {
    "com.animaapp.stc-sketch-plugin": {
      "kModelPropertiesKey": {
        "isCollapsing": 1,
        "resizesContainer": 1,
        "spacing": 4,
        "stackType": 1
      },
      "kViewTypeKey": "ADModelStackView"
    }
  }
}