{
  "_class": "artboard",
  "backgroundColor": {
    "_class": "color",
    "alpha": 0.92,
    "blue": 0,
    "do_objectID": "5BE1FE33-7E28-461E-89AD-9B42D161C908",
    "green": 0,
    "red": 0
  },
  "booleanOperation": -1,
  "clippingMaskMode": 0,
  "do_objectID": "534CC716-0BEE-4716-AB51-B8751EFA85BE",
  "exportOptions": {
    "_class": "exportOptions",
    "do_objectID": "87771AE5-2E3A-44F8-B29B-D67875F57CFF",
    "exportFormats": [
    ],
    "includedLayerIds": [
    ],
    "layerOptions": 0,
    "shouldTrim": false
  },
  "frame": {
    "_class": "rect",
    "constrainProportions": false,
    "do_objectID": "1E323F93-9DF0-4FB5-8A33-B903D65A4C31",
    "height": 768,
    "width": 1440,
    "x": 17759,
    "y": 3169
  },
  "hasBackgroundColor": true,
  "hasClickThrough": false,
  "hasClippingMask": false,
  "horizontalRulerData": {
    "_class": "rulerData",
    "base": 0,
    "do_objectID": "0FFB94FE-9CF1-4D7C-AC5A-5CF2D4729142",
    "guides": [
    ]
  },
  "includeBackgroundColorInExport": true,
  "includeInCloudUpload": true,
  "isFixedToViewport": false,
  "isFlippedHorizontal": false,
  "isFlippedVertical": false,
  "isFlowHome": false,
  "isLocked": false,
  "isVisible": true,
  "layerListExpandedType": 2,
  "layers": [
    {
      "class": "bitmap",
      "id": "82EC3A07-E01F-4B0E-9851-6BDA70D19C46"
    },
    {
      "class": "rectangle",
      "id": "24C5C0C5-98D2-4D99-8687-227FCBB5F874"
    },
    {
      "class": "symbolInstance",
      "id": "208B625E-41B7-44AD-B81A-8805CEE6166D"
    },
    {
      "class": "text",
      "id": "627ECB83-9A9B-4687-A310-C5C0ECFA014F"
    },
    {
      "class": "text",
      "id": "1B00E3D4-374F-4E71-9528-D216991EE7A9"
    },
    {
      "class": "group",
      "id": "24FD7B0C-3B40-4817-9D73-861191893D57"
    }
  ],
  "name": "LD.001-F",
  "nameIsFixed": true,
  "presetDictionary": {
    "allowResizedMatching": 0,
    "height": 768,
    "name": "13.3",
    "offersLandscapeVariant": 0,
    "width": 1440
  },
  "resizesContent": false,
  "resizingConstraint": 63,
  "resizingType": 0,
  "rotation": 0,
  "shouldBreakMaskChain": true,
  "style": {
    "_class": "style",
    "do_objectID": "75FA2632-BCEB-49BD-BE3A-7B0B609802F2",
    "endMarkerType": 0,
    "miterLimit": 10,
    "startMarkerType": 0,
    "windingRule": 1
  },
  "userInfo": {
    "com.animaapp.stc-sketch-plugin": {
      "kModelPropertiesKey": {
      }
    }
  },
  "verticalRulerData": {
    "_class": "rulerData",
    "base": 0,
    "do_objectID": "78F7A13B-93AE-4E7B-8AC3-2B7563951897",
    "guides": [
    ]
  }
}